hat/sbs/evaluator.py
hat/sbs/parser.py
hat/sbs/common.py
hat/sbs/serializer/__init__.py
hat/sbs/repository.py
hat/sbs/serializer/_cserializer.abi3.pyd
hat/sbs/serializer/cserializer.py
hat/sbs/serializer/pyserializer.py
hat/sbs/serializer/common.py
hat/sbs/__init__.py
hat_sbs-0.7.5.dist-info/LICENSE
hat_sbs-0.7.5.dist-info/METADATA
hat_sbs-0.7.5.dist-info/WHEEL
hat_sbs-0.7.5.dist-info/RECORD
