Metadata-Version: 2.1
Name: hat-sbs
Version: 0.7.5
Summary: Hat simple binary serializer
License: Apache-2.0
Classifier: Programming Language :: Python :: 3
Classifier: License :: OSI Approved :: Apache Software License
Provides-Extra: dev
Requires-Dist: hat-json ~=0.6.0
Requires-Dist: hat-peg ~=0.5.10
Requires-Dist: hat-util ~=0.6.17
Requires-Dist: hat-doit ~=0.16.0; extra == 'dev'
Requires-Dist: peru >=1.3.1; extra == 'dev'
Requires-Python: >=3.10
Project-URL: Homepage, http://hat-open.com
Project-URL: Repository, https://github.com/hat-open/hat-sbs.git
Project-URL: Documentation, http://hat-sbs.hat-open.com
